soimt/__init__.py
soimt/main.py
soimt/adversarial_attack_for_optical/__init__.py
soimt/adversarial_attack_for_optical/Cloud_GAN/__init__.py
soimt/adversarial_attack_for_optical/LocalGaussianBlur/__init__.py
soimt/adversarial_attack_for_optical/LocalGaussianBlur/src/LocalGaussianBlur.py
soimt/adversarial_attack_for_optical/LocalGaussianBlur/src/__init__.py
soimt-0.0.1.dist-info/DESCRIPTION.rst
soimt-0.0.1.dist-info/METADATA
soimt-0.0.1.dist-info/RECORD
soimt-0.0.1.dist-info/WHEEL
soimt-0.0.1.dist-info/metadata.json
soimt-0.0.1.dist-info/top_level.txt
