Metadata-Version: 2.0
Name: soimt
Version: 0.0.1
Summary: Evaluate the reliability of image classification models.
Home-page: https://github.com/Agiraffea/model_test_program
Author: BUCT-IST
Author-email: 2023210599@buct.edu.cn
Maintainer: cjlw
Maintainer-email: 2023210599@buct.edu.cn
License: MIT License
Platform: Windows
Classifier: License :: OSI Approved :: MIT License
Classifier: Programming Language :: Python :: 3.11
Requires-Python: >=3.8
Requires-Dist: matplotlib (>3.7.0)
Requires-Dist: numpy (>1.20.0)
Requires-Dist: torch (==2.0.1)
Requires-Dist: torchvision (==0.15.2)
Requires-Dist: tqdm (==4.65.0)
